{
  "syncedAt": "2026-05-08T00:58:16.935Z",
  "blogId": "jmoffice051",
  "count": 24,
  "posts": [
    {
      "logNo": 224277551193,
      "title": "여름철 프린터 관리방법 제대로 알아두세요",
      "brief": "날씨가 더워지고 장마까지 시작되면 집안 전자기기 관리에도 신경을 써야 하는 시기가 됩니다. 특히 사무실이나 가정에서 매일 사용하는 프린터는 여름철 환경 변화에 영향을 많이 받는 기기 중 하나인데요. 실제로 여름철에는 습기와 발열 때문에 출력 오류나 종이 걸림, 토너 이상 같은 문제가 평",
      "category": "정보",
      "thumbnail": "https://mblogthumb-phinf.pstatic.net/MjAyNjA1MDdfMTI5/MDAxNzc4MTIyNzMwOTIy.xu8qkYlh2CGaZOxMbAYjdlLgzrD608JRcke2AJLkLQMg.bRsmJV1gFPwvB9Au1Rb3V_AfLl7DLKfxwK62QiHAX5cg.PNG/%C1%A6%C0%CC%BF%A5%BF%C0%C7%C7%BD%BA.png",
      "date": 1778122841733,
      "url": "https://blog.naver.com/jmoffice051/224277551193",
      "sympathyCnt": 4
    },
    {
      "logNo": 224267971691,
      "title": "부산 컴퓨터 장기렌탈 사무실 운영에 최적화된 장비 구성",
      "brief": "안녕하세요 :D 제이엠오피스입니다 ^^ 사무실을 운영하다 보면 컴퓨터는 가장 기본이 되면서도 업무 효율에 직접적인 영향을 주는 핵심 장비인데요, 특히 장기간 안정적으로 사용해야 하는 경우라면 초기 비용과 유지관리까지 함께 고려해야 합니다. 이런 상황에서 많은 분들이 선택하시는 방법이 바",
      "category": "설치후기",
      "thumbnail": "https://mblogthumb-phinf.pstatic.net/MjAyNjA0MjhfMzEg/MDAxNzc3MzU0NzgyMzU0.IRGmM0XsNB7V8kdHLqaEf_lT9MiCnWfF18fydHEKopQg._Ee7JiSq25fno5_I0F80NZxK6M2nEGQvWQrY_FGJvqQg.PNG/%C1%A6%C0%CC%BF%A5%BF%C0%C7%C7%BD%BA.png",
      "date": 1777354793342,
      "url": "https://blog.naver.com/jmoffice051/224267971691",
      "sympathyCnt": 1
    },
    {
      "logNo": 224263498582,
      "title": "부산 건설사무실 복합기렌탈 A3 출력까지 가능한 최적의 제품으로",
      "brief": "안녕하세요 :D 제이엠오피스입니다 ^^ 건설사무실에서는 도면 출력, 견적서, 공정표 등 다양한 문서를 다루기 때문에 일반 사무실보다 복합기 선택이 훨씬 중요합니다. 특히 A3 출력이 가능한 장비는 필수에 가까운데요, 이런 환경에서 많은 분들이 부산 건설사무실 복합기렌탈을 통해 효율적인 ",
      "category": "설치후기",
      "thumbnail": "https://mblogthumb-phinf.pstatic.net/MjAyNjA0MjRfNzIg/MDAxNzc2OTk5MTI0MzMy.oknyat7dEwga0jPqXMcR6YvPki4bcLCGSEJ_OMnnGXkg.X4OV4cY3lBULujZEbTz7k2GlKbmIx7y60pFIXm9Glisg.PNG/%C1%A6%C0%CC%BF%A5%BF%C0%C7%C7%BD%BA.png",
      "date": 1776999215207,
      "url": "https://blog.naver.com/jmoffice051/224263498582",
      "sympathyCnt": 2
    },
    {
      "logNo": 224262212740,
      "title": "부산 정관 복합기렌탈 사무업무 환경 개선에 도움되는 최적의 모델들로 진행",
      "brief": "안녕하세요 :D 제이엠오피스입니다 ^^ 사무실에서 사용하는 복합기는 단순한 출력 장비를 넘어 업무 효율을 좌우하는 핵심 요소라고 할 수 있습니다. 특히 출력량이 많고 여러 사람이 동시에 사용하는 환경에서는 안정적인 성능과 관리가 중요한데요, 이런 이유로 많은 분들이 부산 정관 복합기렌탈",
      "category": "설치후기",
      "thumbnail": "https://mblogthumb-phinf.pstatic.net/MjAyNjA0MjNfMjM4/MDAxNzc2OTA5MDgxNzQ4.Gh5WvbTo3XAdQqEkI0iOS4SNp2wDHSThJvrYVhlAh9og.i7xJZBE9BW60wew4jvCImwmpC7QN_OJxQuLme0ShGjgg.PNG/%C1%A6%C0%CC%BF%A5%BF%C0%C7%C7%BD%BA.png",
      "date": 1776909163028,
      "url": "https://blog.naver.com/jmoffice051/224262212740",
      "sympathyCnt": 4
    },
    {
      "logNo": 224261157105,
      "title": "양산 복합기렌탈 사무실 가성비 좋은 캐논 MB2720 설치",
      "brief": "안녕하세요 :D 제이엠오피스입니다 ^^ 사무실을 운영하다 보면 출력, 복사, 스캔 업무는 하루에도 여러 번 반복되는 기본 작업인데요. 이런 업무를 안정적으로 처리하기 위해서는 복합기 선택이 매우 중요합니다. 특히 초기 비용 부담 없이 효율적인 환경을 구성하고자 하시는 분들께서는 양산 복",
      "category": "설치후기",
      "thumbnail": "https://mblogthumb-phinf.pstatic.net/MjAyNjA0MjJfOTUg/MDAxNzc2ODMyMDA0OTYy.I4dm2esoB2U5zgkyY9ZVYEKMcsCx70t5tlqBHbLTSQgg.IoJyTVjr4JHmRULr1vB1W8BvVLL64gY_NWfbXiZ-I-sg.PNG/%C1%A6%C0%CC%BF%A5%BF%C0%C7%C7%BD%BA.png",
      "date": 1776832061843,
      "url": "https://blog.naver.com/jmoffice051/224261157105",
      "sympathyCnt": 3
    },
    {
      "logNo": 224259765347,
      "title": "부산 사무용PC렌탈 센텀국제영화제 행사 장비 설치 걱정없이 쉽고 편하게",
      "brief": "안녕하세요 :D 제이엠오피스입니다 ^^ 행사나 프로젝트성 업무에서는 짧은 기간 동안 많은 장비가 필요한 경우가 자주 생기는데요, 특히 국제행사나 운영 인력이 많은 현장에서는 컴퓨터와 출력 장비 구성이 매우 중요합니다. 이런 상황에서 많은 분들이 부산 사무용PC렌탈을 통해 효율적으로 업무",
      "category": "설치후기",
      "thumbnail": "https://mblogthumb-phinf.pstatic.net/MjAyNjA0MjFfOTMg/MDAxNzc2NzM4NTM3NTQ1.uKa13uZi6lqEdXhoyJWlTUo2r4_N5RZFBs_178uQQg8g.Cbo8oWvweve35nLHxXwpmowXNXTwpbyl6YFg7u2PJmUg.PNG/%C1%A6%C0%CC%BF%A5%BF%C0%C7%C7%BD%BA.png",
      "date": 1776738568115,
      "url": "https://blog.naver.com/jmoffice051/224259765347",
      "sympathyCnt": 1
    },
    {
      "logNo": 224258470581,
      "title": "부산 금정구 사무기기렌탈 인테리어회사 디자인 장비 설치",
      "brief": "안녕하세요 :D 제이엠오피스입니다 ^^ 인테리어회사처럼 설계, 도면, 디자인 작업이 많은 환경에서는 일반 사무 장비보다 조금 더 업무 특성에 맞는 장비 구성이 중요합니다. 특히 디자인용 컴퓨터와 대형 모니터, A3 출력이 가능한 복합기까지 함께 구성되어야 업무 효율이 높아지는데요, 이런",
      "category": "설치후기",
      "thumbnail": "https://mblogthumb-phinf.pstatic.net/MjAyNjA0MjBfMjEg/MDAxNzc2NjUwODYyODgz.S5g3RFsXUQ6oVcTruF8J5SnLdsSc2jG_JSRyGo4VSGog.NqXR4MhCZYBOeSQBoIpJaobKZm05g3cgor6iMOCrxqcg.PNG/%C1%A6%C0%CC%BF%A5%BF%C0%C7%C7%BD%BA.png",
      "date": 1776650938161,
      "url": "https://blog.naver.com/jmoffice051/224258470581",
      "sympathyCnt": 1
    },
    {
      "logNo": 224255468186,
      "title": "부산 컴퓨터렌탈 스타트업 사무실 고급 PC 5세트 설치 제이엠오피스에서 신속하게",
      "brief": "안녕하세요 :D 제이엠오피스입니다 ^^ 스타트업 사무실을 처음 구성하거나 인원이 늘어나면서 장비를 추가해야 하는 경우, 빠르게 업무 환경을 구축하는 것이 무엇보다 중요합니다. 특히 컴퓨터와 모니터는 업무 효율과 직결되는 핵심 장비이기 때문에 안정적인 세팅이 필요한데요, 이런 상황에서 많",
      "category": "설치후기",
      "thumbnail": "https://mblogthumb-phinf.pstatic.net/MjAyNjA0MTdfMzMg/MDAxNzc2MzkyMjc3OTkx.RFyksOyDyns6jeQIVlitUjWTrfIzAeKDwRN6sYTQTpog.auooZq21fVdxog18snAhcNJ8Aa6NEcZIjFcbvwesACEg.PNG/%C1%A6%C0%CC%BF%A5%BF%C0%C7%C7%BD%BA.png",
      "date": 1776392293674,
      "url": "https://blog.naver.com/jmoffice051/224255468186",
      "sympathyCnt": 0
    },
    {
      "logNo": 224254206264,
      "title": "경성대 게이밍컴퓨터렌탈 게임연구팀 장비 세팅 사례",
      "brief": "안녕하세요 :D 제이엠오피스입니다 ^^ 최근 대학 내에서도 게임 개발, 테스트, 연구를 위한 환경 구축이 활발해지면서 고성능 장비에 대한 수요가 꾸준히 늘어나고 있습니다. 특히 게임연구팀이나 관련 프로젝트를 진행하는 경우 일반 사무용 컴퓨터로는 한계가 있기 때문에 안정적인 성능을 갖춘 ",
      "category": "설치후기",
      "thumbnail": "https://mblogthumb-phinf.pstatic.net/MjAyNjA0MTZfMTMy/MDAxNzc2MzA0MDk5ODY5.qCFPjSNBSYZHQjlpsIjdjSI9qh8AvDjLDyjYRlnwpOUg.7fUyEE6A2U2nB1VDDNMYLf39yb0IZTTCr0vcG5ZWrw0g.PNG/%C1%A6%C0%CC%BF%A5%BF%C0%C7%C7%BD%BA.png",
      "date": 1776304159085,
      "url": "https://blog.naver.com/jmoffice051/224254206264",
      "sympathyCnt": 0
    },
    {
      "logNo": 224253030881,
      "title": "e스포츠대회 게이밍컴퓨터렌탈 대학 축제 롤 대회 장비 세팅도 제이엠오피스와 함께",
      "brief": "안녕하세요 :D 제이엠오피스입니다 ^^ 최근 대학교 축제나 각종 행사에서 e스포츠대회가 빠지지 않는 콘텐츠로 자리 잡으면서 고성능 장비에 대한 수요도 함께 늘어나고 있는데요, 특히 롤과 같은 게임은 안정적인 프레임과 빠른 반응 속도가 중요하기 때문에 장비 선택이 매우 중요합니다. 이런 ",
      "category": "설치후기",
      "thumbnail": "https://mblogthumb-phinf.pstatic.net/MjAyNjA0MTVfMjkz/MDAxNzc2MjIwNTkwNjc1.OzG796gjfPxlJbiEomUBdzllQD1PqOEOpd__hDTPH40g.J8xdgYhK6uu8C1zFs8l63ZOb6G0zeOuv7o1bpKNrSj4g.PNG/%C1%A6%C0%CC%BF%A5%BF%C0%C7%C7%BD%BA.png",
      "date": 1776220640947,
      "url": "https://blog.naver.com/jmoffice051/224253030881",
      "sympathyCnt": 0
    },
    {
      "logNo": 224251795262,
      "title": "부산 정관복합기렌탈 공장 사무실 HP8710 설치 사례",
      "brief": "안녕하세요 :D 제이엠오피스입니다 ^^ 공장이나 제조업 현장에서는 생산 업무뿐만 아니라 발주서, 출고 자료, 거래명세서, 각종 보고서까지 다양한 문서 작업이 함께 이루어지기 때문에 복합기는 없어서는 안 될 필수 장비입니다. 특히 사무실과 현장이 함께 운영되는 환경에서는 복잡한 기능보다 ",
      "category": "설치후기",
      "thumbnail": "https://mblogthumb-phinf.pstatic.net/MjAyNjA0MTRfMjk5/MDAxNzc2MTM1MDgxNzMx.ks4IXZd0YCBIkzQlu50ou9Iry3TZWdNJ8pxmzSv9mfQg.eaiUYw111WrU48IJdHu1pdpPsrNWJFKjPX97z0vMu3Ig.PNG/%C1%A6%C0%CC%BF%A5%BF%C0%C7%C7%BD%BA.png",
      "date": 1776135116789,
      "url": "https://blog.naver.com/jmoffice051/224251795262",
      "sympathyCnt": 0
    },
    {
      "logNo": 224250509103,
      "title": "부산 동래구 사무기기렌탈 사무실 컴퓨터 12대 복합기 설치 편한 서비스를 만나보세요",
      "brief": "안녕하세요 :D 제이엠오피스입니다 ^^ 사무실 인원이 늘어나거나 업무량이 증가하게 되면 장비 추가 구성이 필요해지는 경우가 많습니다. 특히 컴퓨터와 복합기는 업무의 기본이 되는 장비이기 때문에 빠르고 안정적인 세팅이 중요합니다. 이런 상황에서 많은 분들이 부산 동래구 사무기기렌탈을 통해",
      "category": "설치후기",
      "thumbnail": "https://mblogthumb-phinf.pstatic.net/MjAyNjA0MTNfMTk5/MDAxNzc2MDQ5MTE5NDMy.EeGgZcwFDozZFynlb9vP7doW79h2I2TwT1bzH1HKcVEg.TXeFtm8qeAhUwrzJ8_G3fyFOE5ybOcJVujOLr6fjlSwg.PNG/%C1%A6%C0%CC%BF%A5%BF%C0%C7%C7%BD%BA.png",
      "date": 1776049166711,
      "url": "https://blog.naver.com/jmoffice051/224250509103",
      "sympathyCnt": 0
    },
    {
      "logNo": 224247548789,
      "title": "센텀 컴퓨터렌탈 사무실 5세트 32인치 모니터 설치 사례",
      "brief": "안녕하세요 :D 제이엠오피스입니다 ^^ 사무실을 새롭게 구성하거나 인원 증가로 장비가 추가로 필요한 경우, 빠르게 업무 환경을 구축하는 것이 중요합니다. 특히 컴퓨터와 모니터는 업무 효율에 직접적인 영향을 주는 핵심 장비이기 때문에 안정적인 구성과 세팅이 필요합니다. 이런 상황에서 많은",
      "category": "설치후기",
      "thumbnail": "https://mblogthumb-phinf.pstatic.net/MjAyNjA0MTBfMTQ1/MDAxNzc1Nzg5MTU3NTYz.UcdPcJqebEQQEXRHO76z7RioM561B_exOl24ooE89cAg.24V-OMrV7jjesTugL4eGHehNxtQRXfVDNHdOJi7IGPwg.PNG/%C1%A6%C0%CC%BF%A5%BF%C0%C7%C7%BD%BA.png",
      "date": 1775789268104,
      "url": "https://blog.naver.com/jmoffice051/224247548789",
      "sympathyCnt": 1
    },
    {
      "logNo": 224246243603,
      "title": "부산 남천동 학원 복합기렌탈 수학학원 맞춤 장비로 더 편하게",
      "brief": "안녕하세요 :D 제이엠오피스입니다 ^^ 학원에서는 교재 출력, 시험지 제작, 자료 복사 등 문서 작업이 매우 빈번하게 이루어지기 때문에 복합기 선택이 정말 중요한데요, 특히 출력량이 많은 수학학원 같은 경우에는 안정적인 장비 구성이 필수입니다. 이런 환경에서 많은 분들이 부산 남천동 학",
      "category": "설치후기",
      "thumbnail": "https://mblogthumb-phinf.pstatic.net/MjAyNjA0MDlfNjAg/MDAxNzc1NzAxMjM3MDMw.NEFj3KU8QHA6TqeLl8g3f57q3A5-19fgDz1ap_Hv0fkg._v7VV8Fx7KzWs9OUqob-t1isvuS3LW0cNC3WpNL4i-Qg.PNG/%C1%A6%C0%CC%BF%A5%BF%C0%C7%C7%BD%BA.png",
      "date": 1775701346384,
      "url": "https://blog.naver.com/jmoffice051/224246243603",
      "sympathyCnt": 1
    },
    {
      "logNo": 224244947945,
      "title": "부산 서면 사무실 사무기기렌탈 효율적인 장비 구성 설치",
      "brief": "안녕하세요 :D 제이엠오피스입니다 ^^ 사무실을 운영하다 보면 출력 장비와 업무용 PC 환경은 기본이면서도 가장 중요한 요소가 되는데요, 특히 초기 세팅 단계에서는 어떤 장비를 선택하느냐에 따라 업무 효율이 크게 달라지게 됩니다. 이런 이유로 많은 분들이 부산 서면 사무실 사무기기렌탈을",
      "category": "설치후기",
      "thumbnail": "https://mblogthumb-phinf.pstatic.net/MjAyNjA0MDhfMzYg/MDAxNzc1NjE0MDgwNDk3.Qu0E97UBkEbbdB8F3LqE6c9qkefDw-T_MFMwBGDPl74g.FAhDr-SJuDAj4w4fDVdh4YOd7rWegucISsAbA7kQec0g.PNG/%C1%A6%C0%CC%BF%A5%BF%C0%C7%C7%BD%BA.png",
      "date": 1775614117889,
      "url": "https://blog.naver.com/jmoffice051/224244947945",
      "sympathyCnt": 1
    },
    {
      "logNo": 224243617509,
      "title": "울산대학교 복합기렌탈 공공기관에서도 찾아주시는 제이엠오피스",
      "brief": "안녕하세요 :D 제이엠오피스입니다 ^^ 학교나 학부 사무실에서는 문서 출력, 자료 복사, 스캔 등 다양한 업무가 동시에 이루어지기 때문에 안정적인 복합기 선택이 무엇보다 중요합니다. 특히 학생과 교직원이 함께 사용하는 환경에서는 장비의 내구성과 속도가 업무 효율을 좌우하게 되는데요, 이",
      "category": "설치후기",
      "thumbnail": "https://mblogthumb-phinf.pstatic.net/MjAyNjA0MDdfMTI0/MDAxNzc1NTI2MDczMTgz.4m5MTfRB1yLQYay3tW84xe_hJw0OEK4v1QYW6aClOvAg.uOjd9_ICM-FweJ1rI30XBsnxFXMco9HcXen0JIHpmKcg.PNG/%C1%A6%C0%CC%BF%A5%BF%C0%C7%C7%BD%BA.png",
      "date": 1775545200000,
      "url": "https://blog.naver.com/jmoffice051/224243617509",
      "sympathyCnt": 0
    },
    {
      "logNo": 224242308936,
      "title": "부산 강서구 선거사무실 사무기기렌탈 55인치 TV 단기 설치",
      "brief": "안녕하세요 :D 제이엠오피스입니다 ^^ 지방선거가 가까워질수록 선거사무실 준비로 바빠지시는 분들이 많아지고 있는데요, 짧은 기간 동안 집중적으로 운영되는 만큼 빠른 장비 세팅과 안정적인 환경 구축이 무엇보다 중요합니다. 이런 상황에서 많은 분들이 선택하시는 방법이 바로 부산 강서구 선거",
      "category": "설치후기",
      "thumbnail": "https://mblogthumb-phinf.pstatic.net/MjAyNjA0MDZfMjQ2/MDAxNzc1NDQwMDUxODky.6ld9jbU5wyAb6fFgfvdYDqg2rtPRNr5oNtBACuWCBlkg.GP3Vw9pf2e9iiaY17xUkLj5HSlAFZCdXiefPEZC7Obog.PNG/%C1%A6%C0%CC%BF%A5%BF%C0%C7%C7%BD%BA.png",
      "date": 1775440133118,
      "url": "https://blog.naver.com/jmoffice051/224242308936",
      "sympathyCnt": 0
    },
    {
      "logNo": 224239324612,
      "title": "부산 센텀시티 복합기렌탈 사무실 컬러복합기 설치 신속하고 편리하게",
      "brief": "안녕하세요 :D 제이엠오피스입니다 ^^ 사무실에서 가장 기본이 되면서도 업무 효율에 큰 영향을 주는 장비가 바로 복합기인데요, 특히 출력량이 많은 환경에서는 안정적인 성능과 속도를 갖춘 장비 선택이 중요합니다. 이런 이유로 많은 분들이 부산 센텀시티 복합기렌탈을 통해 효율적인 사무실 환",
      "category": "설치후기",
      "thumbnail": "https://mblogthumb-phinf.pstatic.net/MjAyNjA0MDNfMjMg/MDAxNzc1MTgzODMwMTQy.U6jr1y7JA1rylTV52dRgVF5chx0GpSw_NGjlXR-xxpAg.HNr3jdPzt8YwE9EERfOw-JvXS--kGMTiZv9cVRj_pg0g.PNG/%C1%A6%C0%CC%BF%A5%BF%C0%C7%C7%BD%BA.png",
      "date": 1775183864102,
      "url": "https://blog.naver.com/jmoffice051/224239324612",
      "sympathyCnt": 0
    },
    {
      "logNo": 224238150376,
      "title": "부산 문현금융단지 BIFC2 복합기렌탈 사무실 장비 세팅 사례",
      "brief": "안녕하세요 :D 제이엠오피스입니다 ^^ 사무실을 새롭게 오픈하시거나 장비 교체가 필요한 시점에는 어떤 장비를 선택해야 할지 고민이 많아지는데요, 특히 출력과 문서 관리가 중요한 업무 환경에서는 안정적인 복합기와 프린터 구성이 필수입니다. 이런 상황에서 많은 분들이 선택하시는 방법이 바로",
      "category": "설치후기",
      "thumbnail": "https://mblogthumb-phinf.pstatic.net/MjAyNjA0MDJfMTc5/MDAxNzc1MTAxNzM0OTE0.mSZVI24i-qfrym30x9kamGfxsSuVXBoLxbxJFQRihzIg.Y957cRnaOtahNnSlQrkny8tLX60MgWuLB6P1tHvBZ7Ig.PNG/%C1%A6%C0%CC%BF%A5%BF%C0%C7%C7%BD%BA.png",
      "date": 1775101770496,
      "url": "https://blog.naver.com/jmoffice051/224238150376",
      "sympathyCnt": 0
    },
    {
      "logNo": 224236770130,
      "title": "양산 TV 티비렌탈 55인치 티비 렌탈 각종 사무기기 대여는 제이엠오피스에서",
      "brief": "안녕하세요 :D 제이엠오피스입니다 ^^ 요즘은 행사, 세미나, 매장 운영, 교육 등 다양한 환경에서 대형 디스플레이의 활용도가 점점 높아지고 있는데요, 특히 일정 기간 동안만 필요한 경우에는 구매보다 양산 TV렌탈을 통해 준비하시는 분들이 많이 늘어나고 있습니다. 필요할 때 빠르게 설치",
      "category": "설치후기",
      "thumbnail": "https://mblogthumb-phinf.pstatic.net/MjAyNjA0MDFfODAg/MDAxNzc1MDEwMDg1NDAx.8EyXf6W7Jqwsj4R-mNiMBYDhT_skRy2WaJ4aug_tjjog.Yum7J7BB18SEI8krjyuBnBgfa8hfYdIUVPTikUm5SWcg.PNG/%C1%A6%C0%CC%BF%A5%BF%C0%C7%C7%BD%BA.png",
      "date": 1775010122714,
      "url": "https://blog.naver.com/jmoffice051/224236770130",
      "sympathyCnt": 1
    },
    {
      "logNo": 224235481144,
      "title": "김해 노트북렌탈 대규모 행사 장비 세팅 제이엠오피스에서 쉽게",
      "brief": "안녕하세요 :D 제이엠오피스입니다 ^^ 대형 행사나 세미나, 박람회가 진행될 때 가장 중요한 요소 중 하나가 바로 장비 준비입니다. 특히 많은 인원이 동시에 사용하는 환경에서는 노트북 수량 확보와 안정적인 세팅이 무엇보다 중요해지는데요, 이런 상황에서 많은 분들이 선택하시는 방법이 바로",
      "category": "설치후기",
      "thumbnail": "https://mblogthumb-phinf.pstatic.net/MjAyNjAzMzFfMTkz/MDAxNzc0OTI0Nzg2NDQ5.EvXhf6dGD3f1D1EgLzjpTUfM6YZOAMoyHVtmJzONkNkg.wtHGZzDisNnrwDrDknNoCn4Z_Jp4oZWvDsm4HD29YWgg.PNG/%C1%A6%C0%CC%BF%A5%BF%C0%C7%C7%BD%BA.png",
      "date": 1774924851870,
      "url": "https://blog.naver.com/jmoffice051/224235481144",
      "sympathyCnt": 0
    },
    {
      "logNo": 224234144088,
      "title": "부산 노트북렌탈 벡스코 행사 단기 대량대여 세팅",
      "brief": "안녕하세요 :D 제이엠오피스입니다 ^^ 벡스코처럼 대형 행사와 세미나, 교육 일정이 꾸준히 진행되는 공간에서는 단기간에 많은 장비를 준비해야 하는 상황이 자주 발생합니다. 특히 참여 인원이 많은 행사일수록 장비 준비 속도와 안정성이 전체 일정에 직접적인 영향을 주기 때문에 사전에 철저한",
      "category": "설치후기",
      "thumbnail": "https://mblogthumb-phinf.pstatic.net/MjAyNjAzMzBfNDEg/MDAxNzc0ODM3OTA0MDE1.wn0zr_D54ZW8rXXKWVyOs6fYLmZ16vat58cwVJFM3yUg.fbsgWUp1HbFPC3jXXdn0tA40wnbN1avCSVUbHpUrUzYg.PNG/%C1%A6%C0%CC%BF%A5%BF%C0%C7%C7%BD%BA.png",
      "date": 1774837917893,
      "url": "https://blog.naver.com/jmoffice051/224234144088",
      "sympathyCnt": 3
    },
    {
      "logNo": 224231271189,
      "title": "부산 컨벤션센터 사무기기렌탈 대규모 행사 장비 세팅",
      "brief": "안녕하세요 :D 제이엠오피스입니다 ^^ 대형 행사나 세미나, 박람회가 진행되는 컨벤션센터에서는 단기간에 많은 장비를 준비해야 하기 때문에 빠르고 안정적인 세팅이 매우 중요합니다. 특히 수십 대 이상의 장비가 동시에 필요한 경우에는 부산 컨벤션센터 사무기기렌탈을 통해 한 번에 준비하는 것",
      "category": "설치후기",
      "thumbnail": "https://mblogthumb-phinf.pstatic.net/MjAyNjAzMjdfMTgz/MDAxNzc0NTc5NjgyOTk5.8krbs0PZfxzG-O1xfOiyS0vcZt1x6vS-1MIwbYYo0fYg.5Q4wAuDAj_NIU5WeLXdttqnKIypbOviXK9sDCUcppaMg.PNG/%C1%A6%C0%CC%BF%A5%BF%C0%C7%C7%BD%BA.png",
      "date": 1774579699008,
      "url": "https://blog.naver.com/jmoffice051/224231271189",
      "sympathyCnt": 4
    },
    {
      "logNo": 224230113143,
      "title": "부산 롯데호텔 TV렌탈 당일 설치·회수까지 빠르게",
      "brief": "안녕하세요 :D 제이엠오피스입니다 ^^ 행사나 미팅, 세미나 등 다양한 일정이 진행되는 호텔에서는 대형 디스플레이 장비가 필요한 경우가 많은데요, 특히 하루 단위로 진행되는 일정이라면 구매보다는 부산 롯데호텔 TV렌탈을 통해 효율적으로 준비하시는 것이 가장 합리적인 선택입니다. 이번 현",
      "category": "설치후기",
      "thumbnail": "https://mblogthumb-phinf.pstatic.net/MjAyNjAzMjZfMjc4/MDAxNzc0NDkzODAyMTIy.NoC02Ewnc4202rTCGGjqwGswZSLPAw7Df36SgUM9FNgg.Mb8-YQ3SyHNSJSg397PsBPFl66co90a-Whp3DqwuZXsg.PNG/%C1%A6%C0%CC%BF%A5%BF%C0%C7%C7%BD%BA.png",
      "date": 1774493874954,
      "url": "https://blog.naver.com/jmoffice051/224230113143",
      "sympathyCnt": 2
    }
  ]
}
